textract_pycon_app/__init__.py
textract_pycon_app/__main__.py
textract_pycon_app/py.typed
textract_pycon_app/textract_pycon_app.py
textract_pycon_app-0.1.2.dist-info/WHEEL
textract_pycon_app-0.1.2.dist-info/entry_points.txt
textract_pycon_app-0.1.2.dist-info/METADATA
textract_pycon_app-0.1.2.dist-info/RECORD
