Metadata-Version: 2.3
Name: textract-pycon-app
Version: 0.1.2
Summary: App example for PyCon
Author: Carlo van Overbeek
Author-email: Carlo van Overbeek <cvanoverbeek@schubergphilis.com>
Classifier: License :: OSI Approved :: Apache Software License
Classifier: Programming Language :: Python :: 3.12
Requires-Dist: textract-pycon>=0.1.0
Requires-Python: >=3.12
